np_jobs-0.0.9.dist-info/METADATA
np_jobs-0.0.9.dist-info/WHEEL
np_jobs-0.0.9.dist-info/entry_points.txt
np_jobs/__init__.py
np_jobs/jobs/__init__.py
np_jobs/jobs/base.py
np_jobs/jobs/pipeline_sorting.py
np_jobs/queues/.mypy_cache/.gitignore
np_jobs/queues/.mypy_cache/3.8/@plugins_snapshot.json
np_jobs/queues/.mypy_cache/3.8/__future__.data.json
np_jobs/queues/.mypy_cache/3.8/__future__.meta.json
np_jobs/queues/.mypy_cache/3.8/_ast.data.json
np_jobs/queues/.mypy_cache/3.8/_ast.meta.json
np_jobs/queues/.mypy_cache/3.8/_codecs.data.json
np_jobs/queues/.mypy_cache/3.8/_codecs.meta.json
np_jobs/queues/.mypy_cache/3.8/_collections_abc.data.json
np_jobs/queues/.mypy_cache/3.8/_collections_abc.meta.json
np_jobs/queues/.mypy_cache/3.8/_thread.data.json
np_jobs/queues/.mypy_cache/3.8/_thread.meta.json
np_jobs/queues/.mypy_cache/3.8/_typeshed/__init__.data.json
np_jobs/queues/.mypy_cache/3.8/_typeshed/__init__.meta.json
np_jobs/queues/.mypy_cache/3.8/_warnings.data.json
np_jobs/queues/.mypy_cache/3.8/_warnings.meta.json
np_jobs/queues/.mypy_cache/3.8/_winapi.data.json
np_jobs/queues/.mypy_cache/3.8/_winapi.meta.json
np_jobs/queues/.mypy_cache/3.8/abc.data.json
np_jobs/queues/.mypy_cache/3.8/abc.meta.json
np_jobs/queues/.mypy_cache/3.8/builtins.data.json
np_jobs/queues/.mypy_cache/3.8/builtins.meta.json
np_jobs/queues/.mypy_cache/3.8/codecs.data.json
np_jobs/queues/.mypy_cache/3.8/codecs.meta.json
np_jobs/queues/.mypy_cache/3.8/collections/__init__.data.json
np_jobs/queues/.mypy_cache/3.8/collections/__init__.meta.json
np_jobs/queues/.mypy_cache/3.8/collections/abc.data.json
np_jobs/queues/.mypy_cache/3.8/collections/abc.meta.json
np_jobs/queues/.mypy_cache/3.8/contextlib.data.json
np_jobs/queues/.mypy_cache/3.8/contextlib.meta.json
np_jobs/queues/.mypy_cache/3.8/dataclasses.data.json
np_jobs/queues/.mypy_cache/3.8/dataclasses.meta.json
np_jobs/queues/.mypy_cache/3.8/datetime.data.json
np_jobs/queues/.mypy_cache/3.8/datetime.meta.json
np_jobs/queues/.mypy_cache/3.8/doctest.data.json
np_jobs/queues/.mypy_cache/3.8/doctest.meta.json
np_jobs-0.0.9.dist-info/RECORD
